{"name":"Full text box register whit excel","id":"practice-register-qa-form-demoqa;full-text-box-register-whit-excel","testSteps":[{"number":1,"description":"Given that a web user wants to practice register form in demoqa","duration":63364,"startTime":"2021-07-09T10:03:52.733-05:00[America/Bogota]","screenshots":[{"screenshot":"72804ed9061bc64e00a72d03a204d8c49ad03f32e5d7aa4b3613ddf72ce1cd13.png","timeStamp":1625843096096}],"result":"SUCCESS","precondition":false,"level":0,"children":[{"number":2,"description":"Isabel opens the https://demoqa.com/automation-practice-form","duration":61023,"startTime":"2021-07-09T10:03:54.501-05:00[America/Bogota]","screenshots":[{"screenshot":"72804ed9061bc64e00a72d03a204d8c49ad03f32e5d7aa4b3613ddf72ce1cd13.png","timeStamp":1625843095522}],"result":"SUCCESS","precondition":false,"level":1}]},{"number":3,"description":"When he fills all the requested fields in register section whit excel","duration":68389,"startTime":"2021-07-09T10:04:56.104-05:00[America/Bogota]","screenshots":[{"screenshot":"f1a508c34be15461c4c9aa03297b11039356e383358b6634cd7f76bca6d527f3.png","timeStamp":1625843164493}],"result":"SUCCESS","precondition":false,"level":0,"children":[{"number":4,"description":"Isabel fill all fields excel","duration":57131,"startTime":"2021-07-09T10:05:06.986-05:00[America/Bogota]","screenshots":[{"screenshot":"f1a508c34be15461c4c9aa03297b11039356e383358b6634cd7f76bca6d527f3.png","timeStamp":1625843164117}],"result":"SUCCESS","precondition":false,"level":1,"children":[{"number":5,"description":"Isabel enters \u0027Isabel\u0027 into ","duration":4522,"startTime":"2021-07-09T10:05:18.973-05:00[America/Bogota]","screenshots":[{"screenshot":"799ddba2e55492315153f88467ce858c837288d94e4f7ad2bdb56695450ad2e8.png","timeStamp":1625843123495}],"result":"SUCCESS","precondition":false,"level":2},{"number":6,"description":"Isabel enters \u0027Ramos\u0027 into ","duration":3938,"startTime":"2021-07-09T10:05:23.507-05:00[America/Bogota]","screenshots":[{"screenshot":"d2d67b706bae24aecdf6728ff399b2ff3ab5c22a3e4af62c87e53a546bb87609.png","timeStamp":1625843123975},{"screenshot":"cff81077ebc583f855a29b438bfe705805b24414118976a6c45e14536ae03cd2.png","timeStamp":1625843127445}],"result":"SUCCESS","precondition":false,"level":2},{"number":7,"description":"Isabel enters \u0027issabel_214@hotmail.com\u0027 into ","duration":3183,"startTime":"2021-07-09T10:05:27.453-05:00[America/Bogota]","screenshots":[{"screenshot":"cff81077ebc583f855a29b438bfe705805b24414118976a6c45e14536ae03cd2.png","timeStamp":1625843128075},{"screenshot":"ef1a50145ea2afcd64994fc2a24b47b428af87de9175dc59c20ae61ec07c08be.png","timeStamp":1625843130636}],"result":"SUCCESS","precondition":false,"level":2},{"number":8,"description":"Isabel clicks on ","duration":2112,"startTime":"2021-07-09T10:05:30.645-05:00[America/Bogota]","screenshots":[{"screenshot":"dbf8f4555c2225475caa4a4f0e6cea4d90f1e406707e66aac7015af38d4571ba.png","timeStamp":1625843131142},{"screenshot":"02151746d81fa405c36f7f76d5d05e8e561ac9f2b3175ca994a0fb006d84d914.png","timeStamp":1625843132757}],"result":"SUCCESS","precondition":false,"level":2},{"number":9,"description":"Isabel enters \u00273226574533\u0027 into ","duration":2803,"startTime":"2021-07-09T10:05:32.763-05:00[America/Bogota]","screenshots":[{"screenshot":"02151746d81fa405c36f7f76d5d05e8e561ac9f2b3175ca994a0fb006d84d914.png","timeStamp":1625843133347},{"screenshot":"e2ea3a7fd95b748b21094f2df3efb034f10a428ade06bf55460e5272ea23d83e.png","timeStamp":1625843135565}],"result":"SUCCESS","precondition":false,"level":2},{"number":10,"description":"Isabel clicks on ","duration":1767,"startTime":"2021-07-09T10:05:35.571-05:00[America/Bogota]","screenshots":[{"screenshot":"33557c7309fbb39f0e7719b09144bb1facf13807f6823b81a32f352d76bc6c99.png","timeStamp":1625843136000},{"screenshot":"0e76fa1a2b222ebd812821f1fc82aa5d8d2cb9cb0667795c1e376683153406f3.png","timeStamp":1625843137338}],"result":"SUCCESS","precondition":false,"level":2},{"number":11,"description":"Isabel clicks on ","duration":1216,"startTime":"2021-07-09T10:05:37.343-05:00[America/Bogota]","screenshots":[{"screenshot":"0e76fa1a2b222ebd812821f1fc82aa5d8d2cb9cb0667795c1e376683153406f3.png","timeStamp":1625843137768},{"screenshot":"0e76fa1a2b222ebd812821f1fc82aa5d8d2cb9cb0667795c1e376683153406f3.png","timeStamp":1625843138559}],"result":"SUCCESS","precondition":false,"level":2},{"number":12,"description":"Isabel clicks on ","duration":1425,"startTime":"2021-07-09T10:05:38.562-05:00[America/Bogota]","screenshots":[{"screenshot":"0e76fa1a2b222ebd812821f1fc82aa5d8d2cb9cb0667795c1e376683153406f3.png","timeStamp":1625843139007},{"screenshot":"0e76fa1a2b222ebd812821f1fc82aa5d8d2cb9cb0667795c1e376683153406f3.png","timeStamp":1625843139987}],"result":"SUCCESS","precondition":false,"level":2},{"number":13,"description":"Isabel clicks on ","duration":1303,"startTime":"2021-07-09T10:05:39.991-05:00[America/Bogota]","screenshots":[{"screenshot":"0e76fa1a2b222ebd812821f1fc82aa5d8d2cb9cb0667795c1e376683153406f3.png","timeStamp":1625843140420},{"screenshot":"0e76fa1a2b222ebd812821f1fc82aa5d8d2cb9cb0667795c1e376683153406f3.png","timeStamp":1625843141293}],"result":"SUCCESS","precondition":false,"level":2},{"number":14,"description":"Isabel clicks on ","duration":1351,"startTime":"2021-07-09T10:05:41.297-05:00[America/Bogota]","screenshots":[{"screenshot":"0e76fa1a2b222ebd812821f1fc82aa5d8d2cb9cb0667795c1e376683153406f3.png","timeStamp":1625843141751},{"screenshot":"0e76fa1a2b222ebd812821f1fc82aa5d8d2cb9cb0667795c1e376683153406f3.png","timeStamp":1625843142647}],"result":"SUCCESS","precondition":false,"level":2},{"number":15,"description":"Isabel clicks on ","duration":1348,"startTime":"2021-07-09T10:05:42.675-05:00[America/Bogota]","screenshots":[{"screenshot":"0e76fa1a2b222ebd812821f1fc82aa5d8d2cb9cb0667795c1e376683153406f3.png","timeStamp":1625843143105},{"screenshot":"355706b382e175d7b6293ae02fb4c88d3212ca62aa754d3f144afa09d74ac9a2.png","timeStamp":1625843144023}],"result":"SUCCESS","precondition":false,"level":2},{"number":16,"description":"Isabel enters \u0027Arts\u0027 into ","duration":3229,"startTime":"2021-07-09T10:05:44.027-05:00[America/Bogota]","screenshots":[{"screenshot":"dbea6c14b3435c9ed033f6151a867df426e43f5901030c9f2d7591870edcd064.png","timeStamp":1625843144446},{"screenshot":"6908af46aeee4f0eaac2953790df63631655a137ccaba5da2970b41db14ba4be.png","timeStamp":1625843147255}],"result":"SUCCESS","precondition":false,"level":2},{"number":17,"description":"Isabel enters ENTER into ","duration":1649,"startTime":"2021-07-09T10:05:47.264-05:00[America/Bogota]","screenshots":[{"screenshot":"6908af46aeee4f0eaac2953790df63631655a137ccaba5da2970b41db14ba4be.png","timeStamp":1625843147982},{"screenshot":"bb5676d3c546b47275cf17bdbdb38f8d8fe848abcc7f6c8eece52dd1989a69a4.png","timeStamp":1625843148913}],"result":"SUCCESS","precondition":false,"level":2},{"number":18,"description":"Isabel clicks on ","duration":1336,"startTime":"2021-07-09T10:05:49.516-05:00[America/Bogota]","screenshots":[{"screenshot":"331641f9b0f5b120a2cfa8d97d66f2432ada3ba20557d9e0f39beefe78c14e40.png","timeStamp":1625843150010},{"screenshot":"579b04e41c941cad95f57da25bdd1366add94f36adea5fbe1b5951c3eb95a91e.png","timeStamp":1625843150852}],"result":"SUCCESS","precondition":false,"level":2},{"number":19,"description":"Isabel enters \u0027C:\\\\Users\\\\Isabel\\\\Downloads\\\\perfil.png\u0027 into ","duration":973,"startTime":"2021-07-09T10:05:50.859-05:00[America/Bogota]","screenshots":[{"screenshot":"579b04e41c941cad95f57da25bdd1366add94f36adea5fbe1b5951c3eb95a91e.png","timeStamp":1625843151197},{"screenshot":"975f51852bc2b75aea8a8b67dc71cb00e3553f03b8cc13bf67361ac9256d1608.png","timeStamp":1625843151832}],"result":"SUCCESS","precondition":false,"level":2},{"number":20,"description":"Isabel enters \u0027Calle 10 5 A 75\u0027 into ","duration":2268,"startTime":"2021-07-09T10:05:51.836-05:00[America/Bogota]","screenshots":[{"screenshot":"975f51852bc2b75aea8a8b67dc71cb00e3553f03b8cc13bf67361ac9256d1608.png","timeStamp":1625843152164},{"screenshot":"e3aeadf64c68526f1c880c3f9226e99fe8f936df82c5f8c8b5513a082aa10abd.png","timeStamp":1625843154103}],"result":"SUCCESS","precondition":false,"level":2},{"number":21,"description":"Isabel clicks on ","duration":1088,"startTime":"2021-07-09T10:05:54.106-05:00[America/Bogota]","screenshots":[{"screenshot":"e3aeadf64c68526f1c880c3f9226e99fe8f936df82c5f8c8b5513a082aa10abd.png","timeStamp":1625843154456},{"screenshot":"e3aeadf64c68526f1c880c3f9226e99fe8f936df82c5f8c8b5513a082aa10abd.png","timeStamp":1625843155194}],"result":"SUCCESS","precondition":false,"level":2},{"number":22,"description":"Isabel enters \u0027NCR\u0027 into ","duration":2137,"startTime":"2021-07-09T10:05:55.198-05:00[America/Bogota]","screenshots":[{"screenshot":"e3aeadf64c68526f1c880c3f9226e99fe8f936df82c5f8c8b5513a082aa10abd.png","timeStamp":1625843155535},{"screenshot":"bf6ee982f6ecb98cb74c10ed696a80dd9510f76167abe0c43ec07034ec8d951e.png","timeStamp":1625843157335}],"result":"SUCCESS","precondition":false,"level":2},{"number":23,"description":"Isabel enters ENTER into ","duration":969,"startTime":"2021-07-09T10:05:57.338-05:00[America/Bogota]","screenshots":[{"screenshot":"bf6ee982f6ecb98cb74c10ed696a80dd9510f76167abe0c43ec07034ec8d951e.png","timeStamp":1625843157687},{"screenshot":"e7991315f3d3fd7065e180d2df4d30bf910633506ba4cb7c4b0004f4ffc0bf64.png","timeStamp":1625843158307}],"result":"SUCCESS","precondition":false,"level":2},{"number":24,"description":"Isabel clicks on ","duration":1044,"startTime":"2021-07-09T10:05:58.310-05:00[America/Bogota]","screenshots":[{"screenshot":"e7991315f3d3fd7065e180d2df4d30bf910633506ba4cb7c4b0004f4ffc0bf64.png","timeStamp":1625843158669},{"screenshot":"e7991315f3d3fd7065e180d2df4d30bf910633506ba4cb7c4b0004f4ffc0bf64.png","timeStamp":1625843159354}],"result":"SUCCESS","precondition":false,"level":2},{"number":25,"description":"Isabel enters \u0027Delhi\u0027 into ","duration":2167,"startTime":"2021-07-09T10:05:59.357-05:00[America/Bogota]","screenshots":[{"screenshot":"e7991315f3d3fd7065e180d2df4d30bf910633506ba4cb7c4b0004f4ffc0bf64.png","timeStamp":1625843159681},{"screenshot":"48c17a68e1316e1efb09a2f795108391a2fc521b7daab91f072a0901dfa3de1e.png","timeStamp":1625843161523}],"result":"SUCCESS","precondition":false,"level":2},{"number":26,"description":"Isabel enters ENTER into ","duration":929,"startTime":"2021-07-09T10:06:01.527-05:00[America/Bogota]","screenshots":[{"screenshot":"48c17a68e1316e1efb09a2f795108391a2fc521b7daab91f072a0901dfa3de1e.png","timeStamp":1625843161869},{"screenshot":"0deafdb53007e55d4cada257fe9b1e9aaaedbc152522ffb9a16e107f98b4d42b.png","timeStamp":1625843162456}],"result":"SUCCESS","precondition":false,"level":2},{"number":27,"description":"Isabel clicks on ","duration":1308,"startTime":"2021-07-09T10:06:02.459-05:00[America/Bogota]","screenshots":[{"screenshot":"0deafdb53007e55d4cada257fe9b1e9aaaedbc152522ffb9a16e107f98b4d42b.png","timeStamp":1625843162793},{"screenshot":"f1a508c34be15461c4c9aa03297b11039356e383358b6634cd7f76bca6d527f3.png","timeStamp":1625843163767}],"result":"SUCCESS","precondition":false,"level":2}]}]},{"number":28,"description":"Then he should see him data","duration":8126,"startTime":"2021-07-09T10:06:04.497-05:00[America/Bogota]","screenshots":[{"screenshot":"f1a508c34be15461c4c9aa03297b11039356e383358b6634cd7f76bca6d527f3.png","timeStamp":1625843172623}],"result":"SUCCESS","precondition":false,"level":0,"children":[{"number":29,"description":"Isabel validation excel form","duration":3017,"startTime":"2021-07-09T10:06:08.836-05:00[America/Bogota]","screenshots":[{"screenshot":"f1a508c34be15461c4c9aa03297b11039356e383358b6634cd7f76bca6d527f3.png","timeStamp":1625843171852}],"result":"SUCCESS","precondition":false,"level":1,"children":[{"number":30,"description":"Then register form questions should be equalToIgnoringCase(\u0027Thanks for submitting the form\u0027)","duration":1032,"startTime":"2021-07-09T10:06:10.473-05:00[America/Bogota]","screenshots":[{"screenshot":"f1a508c34be15461c4c9aa03297b11039356e383358b6634cd7f76bca6d527f3.png","timeStamp":1625843171504}],"result":"SUCCESS","precondition":false,"level":2}]}]}],"userStory":{"id":"practice-register-qa-form-demoqa","storyName":"Practice register qa form demoqa","path":"src/test/resources/features/registerqa.feature","type":"feature"},"featureTag":{"name":"Features/Practice register qa form demoqa","type":"feature","displayName":"Features/Practice register qa form demoqa"},"title":"Full text box register whit excel","tags":[{"name":"Practice register qa form demoqa","type":"feature","displayName":"Practice register qa form demoqa"},{"name":"scenario1excel","type":"tag","displayName":"scenario1excel"}],"startTime":"2021-07-09T10:03:51.430-05:00[America/Bogota]","duration":141197,"projectKey":"","sessionId":"b08b5b7f5985883a0799e06e70f50221","driver":"chrome","isManualTestingUpToDate":false,"manual":false,"testSource":"Cucumber","actors":[{"name":"Isabel","can":["browse the web"]}],"result":"SUCCESS"}